astrodata/.readthedocs.yaml
astrodata/__init__.py
astrodata/adfactory.py
astrodata/core.py
astrodata/data/README.rst
astrodata/fits.py
astrodata/nddata.py
astrodata/provenance.py
astrodata/testing.py
astrodata/utils.py
astrodata/wcs.py
astrodata-2.10.2.dist-info/LICENSE
astrodata-2.10.2.dist-info/METADATA
astrodata-2.10.2.dist-info/WHEEL
astrodata-2.10.2.dist-info/RECORD
