Metadata-Version: 2.3
Name: astrodata
Version: 2.10.2
Summary: A package for managing astronomical data through a uniform interface
License: BSD3
Author: D. J. Teal
Author-email: dillon.teal@noirlab.com
Requires-Python: >=3.10,<4.0
Classifier: License :: Other/Proprietary License
Classifier: Programming Language :: Python :: 3
Classifier: Programming Language :: Python :: 3.10
Classifier: Programming Language :: Python :: 3.11
Classifier: Programming Language :: Python :: 3.12
Classifier: Programming Language :: Python :: 3.13
Requires-Dist: asdf (>=3.1.0,<4.0.0)
Requires-Dist: astropy (>=6.0.0,<7.0.0)
Requires-Dist: gwcs (>=0.21.0,<0.22.0)
Requires-Dist: jsonschema (>=4.21.1,<5.0.0)
Requires-Dist: numpy (>=1.26.4,<2.0.0)
Project-URL: Documentation, https://geminidrsoftware.github.io/astrodata/
Project-URL: Homepage, https://github.com/GeminiDRSoftware/astrodata/
Project-URL: Repository, https://github.com/GeminiDRSoftware/astrodata/
